objectrocket/__init__.py
objectrocket/acls.py
objectrocket/auth.py
objectrocket/bases.py
objectrocket/client.py
objectrocket/constants.py
objectrocket/errors.py
objectrocket/util.py
objectrocket/instances/__init__.py
objectrocket/instances/elasticsearch.py
objectrocket/instances/mongodb.py
objectrocket/instances/redis.py
objectrocket-0.7.0.dist-info/LICENSE.txt
objectrocket-0.7.0.dist-info/METADATA
objectrocket-0.7.0.dist-info/WHEEL
objectrocket-0.7.0.dist-info/top_level.txt
objectrocket-0.7.0.dist-info/RECORD
