Metadata-Version: 2.1
Name: objectrocket
Version: 0.7.0
Summary: ObjectRocket Python Client
Home-page: https://github.com/objectrocket/python-client/
Author: ObjectRocket Engineering Team
Author-email: anthony.dodd@rackspace.com
License: UNKNOWN
Platform: UNKNOWN
Classifier: Development Status :: 5 - Production/Stable
Classifier: Intended Audience :: Developers
Classifier: Natural Language :: English
Classifier: Operating System :: OS Independent
Classifier: Programming Language :: Python :: 2.7
Classifier: Programming Language :: Python :: 3.7
Classifier: Topic :: Database
Requires-Dist: elasticsearch (>=2.0.0)
Requires-Dist: pymongo (==3.10.1)
Requires-Dist: redis (>=2.0)
Requires-Dist: requests (>=2.0.0)
Requires-Dist: six (<2.0)
Requires-Dist: stevedore
Requires-Dist: futures (==3.0.5)
